{
  "id": 0,
  "fio": "Андреев Гордий Данилович",
  "graid": 3,
  "address": "Краснодар, Красная, д. 139",
  "current_address": "Краснодар, Краснодар, ул. Красная, д. 149",
  "busy_until": 17.0,
  "tasks": [
    {
      "id": 0,
      "name": "Выезд на точку для стимулирования выдач",
      "address": "Краснодар, Краснодар, ул. Красная, д. 176",
      "point": 34,

      "coordinates": [34.14325, 33.32423],
      "route_time": 100,
      "time_start": 9.0,
      "time_finish": 13.0,
      "priority": 3,
      "status": "в работе"
    }
  ]
}
